MANIFEST.in
README
setup.py
django_support_page/__init__.py
django_support_page/forms.py
django_support_page/support_handlers.py
django_support_page/urls.py
django_support_page/views.py
django_support_page.egg-info/PKG-INFO
django_support_page.egg-info/SOURCES.txt
django_support_page.egg-info/dependency_links.txt
django_support_page.egg-info/not-zip-safe
django_support_page.egg-info/top_level.txt
django_support_page/handlers/__init__.py
django_support_page/handlers/mail_handler.py
django_support_page/static/django-support-page/js/browserdetect.js
django_support_page/static/django-support-page/js/detect.js
django_support_page/static/django-support-page/js/domready.js
django_support_page/static/django-support-page/js/events.js
django_support_page/static/django-support-page/js/json2.js
django_support_page/static/django-support-page/js/modernizr-1.6.min.js
django_support_page/templates/django_support_page/form_sent.html
django_support_page/templates/django_support_page/support_form.html
django_support_page/templates/django_support_page/emails/email.txt
django_support_page/templates/django_support_page/emails/email_html.txt